ppss/__init__.py
ppss/ppss.py
ppss-0.2.0.dist-info/LICENSE
ppss-0.2.0.dist-info/METADATA
ppss-0.2.0.dist-info/WHEEL
ppss-0.2.0.dist-info/RECORD
