Metadata-Version: 2.1
Name: ppss
Version: 0.2.0
Summary: Python Protein Subunit Syntax
Home-page: https://github.com/sandyjmacdonald/ppss
License: MIT
Keywords: protein,parser,lark,bioinformatics
Author: sandyjmacdonald
Author-email: sandyjmacdonald@gmail.com
Requires-Python: >=3.7,<4.0
Classifier: License :: OSI Approved :: MIT License
Classifier: Operating System :: OS Independent
Classifier: Programming Language :: Python :: 3
Classifier: Programming Language :: Python :: 3.7
Classifier: Programming Language :: Python :: 3.8
Classifier: Programming Language :: Python :: 3.9
Classifier: Programming Language :: Python :: 3.10
Classifier: Programming Language :: Python :: 3.11
Classifier: Programming Language :: Python :: 3.12
Requires-Dist: lark (>=1.1.0,<2.0.0)
Project-URL: Repository, https://github.com/sandyjmacdonald/ppss
